{
    "main_player": "a",
    "tree_scores": {
        "true(control(a)). true(has(1,2)). true(has(2,2)). true(has(3,3)). true(has(4,0)).": {
            "does(a,remove(1,1)).": 1
        },
        "true(control(b)). true(has(1,1)). true(has(2,2)). true(has(3,3)). true(has(4,0)).": {
            "does(b,remove(2,1)).": 1,
            "does(b,remove(3,3)).": 1,
            "does(b,remove(1,1)).": 1,
            "does(b,remove(2,2)).": 1,
            "does(b,remove(3,1)).": 1,
            "does(b,remove(3,2)).": 1
        },
        "true(control(a)). true(has(1,1)). true(has(2,1)). true(has(3,3)). true(has(4,0)).": {
            "does(a,remove(1,1)).": -1,
            "does(a,remove(3,3)).": 1
        },
        "true(control(b)). true(has(1,0)). true(has(2,1)). true(has(3,3)). true(has(4,0)).": {
            "does(b,remove(2,1)).": 1,
            "does(b,remove(3,2)).": -1
        },
        "true(control(a)). true(has(1,0)). true(has(2,0)). true(has(3,3)). true(has(4,0)).": {
            "does(a,remove(3,3)).": 1
        },
        "true(control(a)). true(has(1,0)). true(has(2,1)). true(has(3,1)). true(has(4,0)).": {
            "does(a,remove(2,1)).": -1
        },
        "true(control(b)). true(has(1,0)). true(has(2,0)). true(has(3,1)). true(has(4,0)).": {
            "does(b,remove(3,1)).": -1
        },
        "true(control(b)). true(has(1,1)). true(has(2,1)). true(has(3,0)). true(has(4,0)).": {
            "does(b,remove(1,1)).": 1
        },
        "true(control(a)). true(has(1,0)). true(has(2,1)). true(has(3,0)). true(has(4,0)).": {
            "does(a,remove(2,1)).": 1
        },
        "true(control(a)). true(has(1,1)). true(has(2,2)). true(has(3,0)). true(has(4,0)).": {
            "does(a,remove(2,2)).": -1,
            "does(a,remove(1,1)).": -1,
            "does(a,remove(2,1)).": 1
        },
        "true(control(b)). true(has(1,1)). true(has(2,0)). true(has(3,0)). true(has(4,0)).": {
            "does(b,remove(1,1)).": -1
        },
        "true(control(b)). true(has(1,0)). true(has(2,2)). true(has(3,0)). true(has(4,0)).": {
            "does(b,remove(2,1)).": 1,
            "does(b,remove(2,2)).": -1
        },
        "true(control(a)). true(has(1,0)). true(has(2,2)). true(has(3,3)). true(has(4,0)).": {
            "does(a,remove(3,3)).": -1,
            "does(a,remove(3,2)).": -1,
            "does(a,remove(3,1)).": 1
        },
        "true(control(b)). true(has(1,0)). true(has(2,2)). true(has(3,1)). true(has(4,0)).": {
            "does(b,remove(3,1)).": 1,
            "does(b,remove(2,1)).": -1,
            "does(b,remove(2,2)).": 1
        },
        "true(control(a)). true(has(1,0)). true(has(2,2)). true(has(3,0)). true(has(4,0)).": {
            "does(a,remove(2,2)).": 1,
            "does(a,remove(2,1)).": -1
        },
        "true(control(b)). true(has(1,0)). true(has(2,2)). true(has(3,2)). true(has(4,0)).": {
            "does(b,remove(2,1)).": 1,
            "does(b,remove(2,2)).": 1
        },
        "true(control(a)). true(has(1,0)). true(has(2,1)). true(has(3,2)). true(has(4,0)).": {
            "does(a,remove(2,1)).": -1,
            "does(a,remove(3,1)).": 1,
            "does(a,remove(3,2)).": -1
        },
        "true(control(b)). true(has(1,0)). true(has(2,0)). true(has(3,2)). true(has(4,0)).": {
            "does(b,remove(3,1)).": 1,
            "does(b,remove(3,2)).": -1
        },
        "true(control(a)). true(has(1,0)). true(has(2,0)). true(has(3,1)). true(has(4,0)).": {
            "does(a,remove(3,1)).": 1
        },
        "true(control(b)). true(has(1,0)). true(has(2,1)). true(has(3,1)). true(has(4,0)).": {
            "does(b,remove(2,1)).": 1
        },
        "true(control(a)). true(has(1,0)). true(has(2,0)). true(has(3,2)). true(has(4,0)).": {
            "does(a,remove(3,1)).": -1,
            "does(a,remove(3,2)).": 1
        },
        "true(control(a)). true(has(1,1)). true(has(2,0)). true(has(3,3)). true(has(4,0)).": {
            "does(a,remove(1,1)).": -1,
            "does(a,remove(3,2)).": 1
        },
        "true(control(b)). true(has(1,0)). true(has(2,0)). true(has(3,3)). true(has(4,0)).": {
            "does(b,remove(3,3)).": -1
        },
        "true(control(b)). true(has(1,1)). true(has(2,0)). true(has(3,1)). true(has(4,0)).": {
            "does(b,remove(1,1)).": 1
        },
        "true(control(a)). true(has(1,1)). true(has(2,2)). true(has(3,2)). true(has(4,0)).": {
            "does(a,remove(1,1)).": 1
        },
        "true(control(b)). true(has(1,0)). true(has(2,1)). true(has(3,0)). true(has(4,0)).": {
            "does(b,remove(2,1)).": -1
        },
        "true(control(a)). true(has(1,1)). true(has(2,2)). true(has(3,1)). true(has(4,0)).": {
            "does(a,remove(2,1)).": -1,
            "does(a,remove(1,1)).": -1,
            "does(a,remove(2,2)).": 1
        },
        "true(control(b)). true(has(1,1)). true(has(2,1)). true(has(3,1)). true(has(4,0)).": {
            "does(b,remove(1,1)).": -1
        }
    }
}